arbow/__init__.py
arbow/__main__.py
arbow/utils.py
arbow/version.py
arbow-0.6.0.dist-info/METADATA
arbow-0.6.0.dist-info/WHEEL
arbow-0.6.0.dist-info/entry_points.txt
arbow-0.6.0.dist-info/top_level.txt
arbow-0.6.0.dist-info/RECORD
