Metadata-Version: 2.1
Name: arbow
Version: 0.6.0
Summary: Cultivate your MSA to get better trees
Home-page: https://github.com/MDPHL/arbow
Author: Microbiological Diagnostic Unit Public Health Laboratory
Author-email: andersgs@gmail.com
License: UNKNOWN
Project-URL: Bug Reports, https://github.com/MDUPHL/arbow/issues
Project-URL: Source, https://github.com/MDUPHL/arbow/
Keywords: bioinformatics phylogenetics multiple sequence alignment msa
Platform: UNKNOWN
Classifier: Development Status :: 3 - Alpha
Classifier: Intended Audience :: Science/Research
Classifier: Topic :: Scientific/Engineering :: Bio-Informatics
Classifier: License :: OSI Approved :: GNU Lesser General Public License v3 (LGPLv3)
Classifier: Programming Language :: Python :: 3.6
Classifier: Programming Language :: Python :: 3.7
Classifier: Programming Language :: Python :: 3.8
Requires-Python: >=3.6, <4
Requires-Dist: pandas
Requires-Dist: click
Requires-Dist: numpy
Requires-Dist: biopython
Requires-Dist: scipy
